disrank/__init__.py
disrank/generator.py
disrank/assets/card.png
disrank/assets/dnd.png
disrank/assets/font.ttf
disrank/assets/font2.ttf
disrank/assets/idle.png
disrank/assets/offline.png
disrank/assets/online.png
disrank/assets/streaming.png
disrank-0.0.2.dist-info/LICENSE
disrank-0.0.2.dist-info/METADATA
disrank-0.0.2.dist-info/WHEEL
disrank-0.0.2.dist-info/top_level.txt
disrank-0.0.2.dist-info/RECORD
